price_parser/__init__.py
price_parser/_currencies.py
price_parser/parser.py
price_parser/py.typed
price_parser-0.3.4.dist-info/LICENSE
price_parser-0.3.4.dist-info/METADATA
price_parser-0.3.4.dist-info/WHEEL
price_parser-0.3.4.dist-info/top_level.txt
price_parser-0.3.4.dist-info/RECORD
