Metadata-Version: 1.1
Name: price-parser
Version: 0.3.4
Summary: Extract price and currency from a raw string
Home-page: https://github.com/scrapinghub/price-parser
Author: Mikhail Korobov
Author-email: kmike84@gmail.com
License: UNKNOWN
Platform: UNKNOWN
Classifier: Development Status :: 4 - Beta
Classifier: Intended Audience :: Developers
Classifier: License :: OSI Approved :: BSD License
Classifier: Natural Language :: English
Classifier: Operating System :: OS Independent
Classifier: Programming Language :: Python :: 3
Classifier: Programming Language :: Python :: 3.6
Classifier: Programming Language :: Python :: 3.7
Classifier: Programming Language :: Python :: 3.8
